django_customflow/__init__.py
django_customflow/mixins.py
django_customflow/models.py
django_customflow/utils.py
django_customflow/conditions/__init__.py
django_customflow/conditions/base.py
django_customflow/migrations/0001_initial.py
django_customflow/migrations/__init__.py
django_customflow/tasks/__init__.py
django_customflow/tasks/base.py
django_customflow-0.1.1.dist-info/DESCRIPTION.rst
django_customflow-0.1.1.dist-info/METADATA
django_customflow-0.1.1.dist-info/RECORD
django_customflow-0.1.1.dist-info/WHEEL
django_customflow-0.1.1.dist-info/metadata.json
django_customflow-0.1.1.dist-info/top_level.txt
